bp_chat_gui/__init__.py
bp_chat-0.0.1.dist-info/METADATA
bp_chat-0.0.1.dist-info/WHEEL
bp_chat-0.0.1.dist-info/top_level.txt
bp_chat-0.0.1.dist-info/RECORD
